bandcamp_lib-0.3.3.dist-info/METADATA
bandcamp_lib-0.3.3.dist-info/WHEEL
bandcamp_lib.libs/libgcc_s-98a1ef30.so.1
bandcamp_lib/__init__.py
bandcamp_lib/bandcamp_lib.pyi
bandcamp_lib/bandcamp_lib.pypy39-pp73-x86_64-linux-gnu.so
bandcamp_lib/py.typed
bandcamp_lib-0.3.3.dist-info/RECORD
