Metadata-Version: 2.4
Name: bandcamp_lib
Version: 0.3.3
Classifier: Programming Language :: Rust
Classifier: Programming Language :: Python :: Implementation :: CPython
Classifier: Programming Language :: Python :: Implementation :: PyPy
Classifier: Intended Audience :: Developers
Classifier: License :: OSI Approved :: MIT License
Classifier: Topic :: Multimedia :: Sound/Audio
Classifier: Topic :: Software Development :: Libraries
Classifier: Typing :: Typed
License-Expression: MIT
Requires-Python: >=3.8
Project-URL: Documentation, https://docs.rs/bandcamp/latest/bandcamp/
Project-URL: Repository, https://github.com/fabi321/bandcamp
Project-URL: Issues, https://github.com/fabi321/bandcamp/issues
